{"name":"build-javascript","namedChunkGroups":{"polyfill":{"name":"polyfill","assets":[{"name":"webpack-runtime-4d1dceb28008699054a2.js","size":5087},{"name":"polyfill-f0de94e6d22b99424ee0.js","size":85854}],"filteredAssets":0,"assetsSize":90941,"filteredAuxiliaryAssets":2,"auxiliaryAssetsSize":228098},"app":{"name":"app","assets":[{"name":"webpack-runtime-4d1dceb28008699054a2.js","size":5087},{"name":"framework-a089095c723b33edebf1.js","size":130230},{"name":"app-f65a13203a16225b93f0.js","size":77120}],"filteredAssets":0,"assetsSize":212437,"filteredAuxiliaryAssets":3,"auxiliaryAssetsSize":683542},"component---src-pages-404-js":{"name":"component---src-pages-404-js","assets":[{"name":"component---src-pages-404-js-1ddaeee59d3a15230553.js","size":817}],"filteredAssets":0,"assetsSize":817,"filteredAuxiliaryAssets":1,"auxiliaryAssetsSize":1876},"component---src-pages-about-js":{"name":"component---src-pages-about-js","assets":[{"name":"styles.dadf522a5dcf3150b4b1.css","size":415},{"name":"component---src-pages-about-js-45bbbd3866707ab09e2d.js","size":1366}],"filteredAssets":0,"assetsSize":1781,"filteredAuxiliaryAssets":1,"auxiliaryAssetsSize":3097},"component---src-pages-index-js":{"name":"component---src-pages-index-js","assets":[{"name":"styles.dadf522a5dcf3150b4b1.css","size":415},{"name":"component---src-pages-index-js-323bef077011b8c3e4c2.js","size":2340}],"filteredAssets":0,"assetsSize":2755,"filteredAuxiliaryAssets":1,"auxiliaryAssetsSize":3308},"component---src-pages-thoughts-js":{"name":"component---src-pages-thoughts-js","assets":[{"name":"styles.dadf522a5dcf3150b4b1.css","size":415},{"name":"component---src-pages-thoughts-js-aadfa573d93f17244800.js","size":4897}],"filteredAssets":0,"assetsSize":5312,"filteredAuxiliaryAssets":1,"auxiliaryAssetsSize":14055}},"assetsByChunkName":{"polyfill":["webpack-runtime-4d1dceb28008699054a2.js","polyfill-f0de94e6d22b99424ee0.js"],"app":["webpack-runtime-4d1dceb28008699054a2.js","framework-a089095c723b33edebf1.js","app-f65a13203a16225b93f0.js"],"component---src-pages-404-js":["component---src-pages-404-js-1ddaeee59d3a15230553.js"],"component---src-pages-about-js":["styles.dadf522a5dcf3150b4b1.css","component---src-pages-about-js-45bbbd3866707ab09e2d.js"],"component---src-pages-index-js":["styles.dadf522a5dcf3150b4b1.css","component---src-pages-index-js-323bef077011b8c3e4c2.js"],"component---src-pages-thoughts-js":["styles.dadf522a5dcf3150b4b1.css","component---src-pages-thoughts-js-aadfa573d93f17244800.js"]},"childAssetsByChunkName":{}}